project1/source/program_counter.v
`timescale 1ns / 1ps
//////////////////////////////////////////////////////////////////////////////////
// ECE4150/6250
// Matthew LaRue 
// Program Counter for MIPS processor
// 
// 
//////////////////////////////////////////////////////////////////////////////////


module program_counter(
    clk,
    rst_n,
    update_msbs,
    update_lsbs,
    jump,
    jump_destination,
    branch,
    branch_offset,
    mem_addr
    );
    
    // declare port directions
    input clk;
    input rst_n;
    input update_msbs;
    input update_lsbs;
    input jump;
    input jump_destination;
    input branch;
    input branch_offset;
    output mem_addr;
    
    // declare port types/sizes
    wire clk;
    wire rst_n;
    wire update_msbs;
    wire update_lsbs;
    wire jump;
    wire [5:0] jump_destination;
    wire branch;
    wire [5:0] branch_offset;
    reg  [7:0] mem_addr;
    
    // internal variables
    reg [7:0] mem_addr_next;
    
    
    // clock iregisters, asynch active-low reset    
    always @(posedge clk or negedge rst_n)
    begin
        if (rst_n == 1'b0) begin
            mem_addr <= 8'h00;
        end else begin
            mem_addr <= mem_addr_next;
        end   
    end
    
    always @(mem_addr, update_msbs, update_lsbs, jump, jump_destination, branch, branch_offset)
    begin
        mem_addr_next = mem_addr;
        
        if (update_msbs == 1'b1) begin
            // use "update_msbs" to progress one instruction, each instruction is 4 memory addresses 
            //    so it counts in increments of 4
            mem_addr_next[7:2] = mem_addr[7:2] + 1'b1;
            mem_addr_next[1:0] = 2'b00;
        end else if (update_lsbs == 1'b1) begin
            // use "update_lsbs" to progress to the next memory address, use it to advance to the next
            //    8 bits of an instruction
            mem_addr_next[1:0] = mem_addr[1:0] + 1'b1;
        end else if (jump == 1'b1) begin
            // use "jump" for the jump command, jumps to the instruction indicated. 
            mem_addr_next[7:2] = jump_destination;
            mem_addr_next[1:0] = 2'b00;
        end else if (branch == 1'b1) begin
            // use "branch" for the "branch if equal" command, branches to 
            //    current instruction number + branch_offset
            mem_addr_next[7:2] = mem_addr[7:2] + branch_offset;
            mem_addr_next[1:0] = 2'b00;
        end
     end
       
endmodule

project1/simulation/testbench/program_counter_tb.v
`timescale 1ns / 1ps

module program_counter_tb(
    );

    initial begin
		$dumpfile("program_counter.vcd");
		$dumpvars(0,program_counter_tb);
	end

    // string to display section labels on waveforms, change its radix 
    //      to ASCII in the waveform to view correctly
    reg     [(20*8)-1:0] str1;      
       
    reg     clk;
    reg     rst_n;
    reg     update_msbs;
    reg     update_lsbs;
    reg     jump;
    reg     [5:0] jump_destination;
    reg     branch;
    reg     [5:0] branch_offset;
    wire    [7:0] mem_addr;
      
    program_counter DUT(
    .clk(clk),
    .rst_n(rst_n),
    .update_msbs(update_msbs),
    .update_lsbs(update_lsbs),
    .jump(jump),
    .jump_destination(jump_destination),
    .branch(branch),
    .branch_offset(branch_offset),
    .mem_addr(mem_addr)
    );
    
        always #5 clk = ~clk;
    
    initial begin
        // initial values
        clk             = 0;
        rst_n           = 1;
        update_msbs     = 0;
        update_lsbs     = 0;
        jump            = 0;
        jump_destination = 6'h00;
        branch          = 0;
        branch_offset   = 6'h00;
        str1            = "Reset_Checks";
        
        // check that reset works
        #12  
        $display ( " mem_addr: Expected %h, Read %h, Time %d" , 8'hXX, mem_addr, $time);
        // activate reset and check
        rst_n       = 0;
        #1
        $display ( " mem_addr: Expected %h, Read %h, Time %d" , 8'h00, mem_addr, $time);
        #10
        $display ( " mem_addr: Expected %h, Read %h, Time %d" , 8'h00, mem_addr, $time);
        // release reset and check
        rst_n       = 1;
        #10
        $display ( " mem_addr: Expected %h, Read %h, Time %d" , 8'h00, mem_addr, $time);
        
        // check updating program counter LSBs for normal operation
        str1            = "LSBs_update";
        update_lsbs     = 1;       
        #10
        $display ( " mem_addr: Expected %h, Read %h, Time %d" , 8'h01, mem_addr, $time);
        update_lsbs     = 0;       
        #10
        $display ( " mem_addr: Expected %h, Read %h, Time %d" , 8'h01, mem_addr, $time);
        update_lsbs     = 1;       
        #10
        $display ( " mem_addr: Expected %h, Read %h, Time %d" , 8'h02, mem_addr, $time);
        #10
        $display ( " mem_addr: Expected %h, Read %h, Time %d" , 8'h03, mem_addr, $time);
        #10
        // update lsbs only iterates bottom two bits, count should loop back arount to 00
        $display ( " mem_addr: Expected %h, Read %h, Time %d" , 8'h00, mem_addr, $time);
        #10
        $display ( " mem_addr: Expected %h, Read %h, Time %d" , 8'h01, mem_addr, $time);
        // stop update lsbs, check that it retains value
        update_lsbs     = 0;       
        #10
        $display ( " mem_addr: Expected %h, Read %h, Time %d" , 8'h01, mem_addr, $time);

        // check updating program counter MSBs for normal operation        
        str1            = "MSBs_update";
        update_msbs     = 1;       
        #10
        $display ( " mem_addr: Expected %h, Read %h, Time %d" , 8'h04, mem_addr, $time);
        update_msbs     = 0;       
        #10
        $display ( " mem_addr: Expected %h, Read %h, Time %d" , 8'h04, mem_addr, $time);
        update_msbs     = 1;       
        #10
        $display ( " mem_addr: Expected %h, Read %h, Time %d" , 8'h08, mem_addr, $time);
        update_msbs     = 0;   
        update_lsbs     = 1;     
        #10
        $display ( " mem_addr: Expected %h, Read %h, Time %d" , 8'h09, mem_addr, $time);      
        #10
        $display ( " mem_addr: Expected %h, Read %h, Time %d" , 8'h0A, mem_addr, $time);
        #10
        $display ( " mem_addr: Expected %h, Read %h, Time %d" , 8'h0B, mem_addr, $time);
        #10
        $display ( " mem_addr: Expected %h, Read %h, Time %d" , 8'h08, mem_addr, $time);
        update_msbs     = 1;   
        update_lsbs     = 0;     
        #10
        $display ( " mem_addr: Expected %h, Read %h, Time %d" , 8'h0C, mem_addr, $time);  
        update_msbs     = 0;
        
        // check jump mode      
        str1            = "Jump"; 
        jump             = 1;
        jump_destination = 6'h0F;
        #10
        $display ( " mem_addr: Expected %h, Read %h, Time %d" , 8'h3C, mem_addr, $time); 
        jump_destination = 6'h0A;
        #10
        $display ( " mem_addr: Expected %h, Read %h, Time %d" , 8'h28, mem_addr, $time); 
        jump             = 0;
        #10
        $display ( " mem_addr: Expected %h, Read %h, Time %d" , 8'h28, mem_addr, $time);
        
        // check branch
        str1            = "Banch"; 
        branch          = 1;
        branch_offset   = 6'h3F;
        #10
        $display ( " mem_addr: Expected %h, Read %h, Time %d" , 8'h24, mem_addr, $time); 
        branch_offset   = 6'h04;
        #10
        $display ( " mem_addr: Expected %h, Read %h, Time %d" , 8'h34, mem_addr, $time);
        branch          = 0;



        #30 
        $finish;         
    end  
    
endmodule

project1/simulation/work/program_counter.vcd
$date
    Sep 19, 2023  23:31:08
$end
$version
    TOOL:	xmsim(64)	17.10-s001
$end
$timescale
    1 ps
$end

$scope module program_counter_tb $end
$var reg      160 !    str1 [159:0] $end
$var reg       1 "    clk $end
$var reg       1 #    rst_n $end
$var reg       1 $    update_msbs $end
$var reg       1 %    update_lsbs $end
$var reg       1 &    jump $end
$var reg       6 '    jump_destination [5:0] $end
$var reg       1 (    branch $end
$var reg       6 )    branch_offset [5:0] $end
$var wire      8 *    mem_addr [7:0] $end

$scope module DUT $end
$var wire      1 +    clk  $end
$var wire      1 ,    rst_n  $end
$var wire      1 -    update_msbs  $end
$var wire      1 .    update_lsbs  $end
$var wire      1 /    jump  $end
$var wire      6 0    jump_destination [5:0] $end
$var wire      1 1    branch  $end
$var wire      6 2    branch_offset [5:0] $end
$var reg       8 3    mem_addr [7:0] $end
$var reg       8 4    mem_addr_next [7:0] $end
$upscope $end

$upscope $end

$enddefinitions $end
$dumpvars
b10100100110010101110011011001010111010001011111010000110110100001100101011000110110101101110011 !
0"
1#
0$
0%
0&
b0 '
0(
b0 )
bx *
0+
1,
0-
0.
0/
b0 0
01
b0 2
bx 3
bx 4
$end
#5000
1"
1+
#10000
0"
0+
#12000
0#
0,
b0 3
b0 4
b0 *
#15000
1"
1+
#20000
0"
0+
#23000
1#
1,
#25000
1"
1+
#30000
0"
0+
#33000
b100110001010011010000100111001101011111011101010111000001100100011000010111010001100101 !
1%
1.
b1 4
#35000
1"
1+
b1 3
b10 4
b1 *
#40000
0"
0+
#43000
0%
0.
b1 4
#45000
1"
1+
#50000
0"
0+
#53000
1%
1.
b10 4
#55000
1"
1+
b10 3
b11 4
b10 *
#60000
0"
0+
#65000
1"
1+
b11 3
b0 4
b11 *
#70000
0"
0+
#75000
1"
1+
b0 3
b1 4
b0 *
#80000
0"
0+
#85000
1"
1+
b1 3
b10 4
b1 *
#90000
0"
0+
#93000
0%
0.
b1 4
#95000
1"
1+
#100000
0"
0+
#103000
b100110101010011010000100111001101011111011101010111000001100100011000010111010001100101 !
1$
1-
b101 4
b100 4
#105000
1"
1+
b100 3
b1000 4
b100 *
#110000
0"
0+
#113000
0$
0-
b100 4
#115000
1"
1+
#120000
0"
0+
#123000
1$
1-
b1000 4
#125000
1"
1+
b1000 3
b1100 4
b1000 *
#130000
0"
0+
#133000
0$
1%
1.
0-
b1000 4
b1001 4
#135000
1"
1+
b1001 3
b1010 4
b1001 *
#140000
0"
0+
#145000
1"
1+
b1010 3
b1011 4
b1010 *
#150000
0"
0+
#155000
1"
1+
b1011 3
b1000 4
b1011 *
#160000
0"
0+
#165000
1"
1+
b1000 3
b1001 4
b1000 *
#170000
0"
0+
#173000
1$
0%
0.
1-
b1000 4
b1100 4
#175000
1"
1+
b1100 3
b10000 4
b1100 *
#180000
0"
0+
#183000
0$
b1001010011101010110110101110000 !
1&
b1111 '
b1111 0
1/
0-
b1100 4
b111100 4
#185000
1"
1+
b111100 3
b111100 *
#190000
0"
0+
#193000
b1010 '
b1010 0
b101000 4
#195000
1"
1+
b101000 3
b101000 *
#200000
0"
0+
#203000
0&
0/
#205000
1"
1+
#210000
0"
0+
#213000
b100001001100001011011100110001101101000 !
1(
b111111 )
b111111 2
11
b100100 4
#215000
1"
1+
b100100 3
b100000 4
b100100 *
#220000
0"
0+
#223000
b100 )
b100 2
b100100 4
b110100 4
#225000
1"
1+
b110100 3
b1000100 4
b110100 *
#230000
0"
0+
#233000
0(
01
b110100 4
