project2/source/tail_light_sequencer.v
`timescale 1ns / 1ps
//////////////////////////////////////////////////////////////////////////////////
// ECE4150/6250
// Yihui Wang 
// Taillight sequencer for Mustang
// 
// 
//////////////////////////////////////////////////////////////////////////////////


module tail_light_sequencer (
    input wire clk,
    input wire rst_n,
    input wire brake,
    input wire turn_right,
    input wire turn_left,

    output reg [2:0] right_tail_light_controll = 0,
    output reg [2:0] left_tail_light_controll = 0
);

    

    // State defination
    parameter idle = 5'b00000;
    parameter brake_only = 5'b00001;
    parameter right_only = 5'b00010;
    parameter left_only = 5'b00100;
    parameter brake_right = 5'b01000;
    parameter brake_left = 5'b10000;

    // State register
    reg [4:0] state = 0, next = 0;

    always @(posedge clk or negedge rst_n) begin
        if (rst_n == 1'b0) begin
            state <= idle;
        end
        else state <= next;
    end

    // State transition logic
    always @(*) begin
        case ({brake,turn_left,turn_right})
            3'b001: next = right_only;
            3'b010: next = left_only;
            3'b100: next = brake_only;
            3'b101: next = brake_right;
            3'b110: next = brake_left;
            default: next = idle;
        endcase
    end

    // Stage cycle counter
    wire next_stage;
    reg [4:0] counter = 5'b00001;

    always @(posedge clk or negedge rst_n) begin
        if ((rst_n == 1'b0) | (next != state)) begin
            counter <= 5'b00001;
        end
        else begin
            if (counter == 5'b10000) begin
                counter <= 5'b00001;
            end
            else begin
                counter <= counter << 1;
            end
        end
    end

    assign next_stage = (counter == 5'b10000);

    // Light output controll
    reg [2:0] right_tail_light_controll_next = 0;
    reg [2:0] left_tail_light_controll_next = 0;

    always @(posedge clk, negedge rst_n) begin
        if (rst_n == 1'b0) begin
            right_tail_light_controll <= 3'b0;
            left_tail_light_controll <= 3'b0;
        end
        else begin
            right_tail_light_controll <= right_tail_light_controll_next;
            left_tail_light_controll <= left_tail_light_controll_next;
        end
    end

    // Light output transition logic
    always @(*) begin
        
        case (next)

            brake_only: begin
                right_tail_light_controll_next <= 3'b111;
                left_tail_light_controll_next <= 3'b111;
            end

            right_only: begin
                if (state == right_only) begin
                    if (next_stage) begin
                        right_tail_light_controll_next <= {right_tail_light_controll[1:0],right_tail_light_controll[2]} + 3'd1;
                    end
                    else begin
                        right_tail_light_controll_next <= right_tail_light_controll;                           
                    end 
                    left_tail_light_controll_next <= 3'b0;
                end
                else begin
                    right_tail_light_controll_next <= 3'b001;
                    left_tail_light_controll_next <= 3'b0;
                end
            end

            left_only: begin
                if (state == left_only) begin
                    if (next_stage) begin
                        left_tail_light_controll_next <= {left_tail_light_controll[1:0],left_tail_light_controll[2]} + 3'd1;
                    end
                    else begin
                        left_tail_light_controll_next <= left_tail_light_controll;
                    end 
                    right_tail_light_controll_next <= 3'b0;
                end
                else begin
                    left_tail_light_controll_next <= 3'b001;
                    right_tail_light_controll_next <= 3'b0;
                end
            end

            brake_right: begin
                if (state == brake_right) begin
                    if (next_stage) begin
                        right_tail_light_controll_next <= {right_tail_light_controll[1:0],right_tail_light_controll[2]} - 3'd1;
                    end
                    else begin
                        right_tail_light_controll_next <= right_tail_light_controll;                           
                    end 
                    left_tail_light_controll_next <= 3'b111;
                end
                else begin
                    right_tail_light_controll_next <= 3'b111;
                    left_tail_light_controll_next <= 3'b111;
                end
            end

            brake_left: begin
                if (state == brake_left) begin
                    if (next_stage) begin
                        left_tail_light_controll_next <= {left_tail_light_controll[1:0],left_tail_light_controll[2]} - 3'd1;
                    end
                    else begin
                        left_tail_light_controll_next <= left_tail_light_controll;
                    end 
                    right_tail_light_controll_next <= 3'b111;
                end
                else begin
                    left_tail_light_controll_next <= 3'b111;
                    right_tail_light_controll_next <= 3'b111;
                end
            end

            default: begin
                right_tail_light_controll_next <= 3'b0;
                left_tail_light_controll_next <= 3'b0;
            end
            
        endcase
    end

endmodule

project2/simulation/testbench/tail_light_sequencer_tb.v
`timescale 1ns / 1ps

module tail_light_sequencer_tb ();

    initial begin
		$dumpfile("tail_light_sequencer_tb.vcd");
		$dumpvars(0,tail_light_sequencer_tb);
	end

    reg clk = 0;
    reg rst_n = 0;
    reg brake = 0;
    reg turn_left = 0;
    reg turn_right = 0;

    wire [2:0] right_tail_light_controll;
    wire [2:0] left_tail_light_controll;

    tail_light_sequencer sequencer(
        .clk(clk),
        .rst_n(rst_n),
        .brake(brake),
        .turn_right(turn_right),
        .turn_left(turn_left),
        .right_tail_light_controll(right_tail_light_controll),
        .left_tail_light_controll(left_tail_light_controll)
    );

    always begin
        #1 
        clk = ~clk;
        $display ( "Brake = %b, turn_right = %b, turn_left = %b, right_tail_light = %b, left_tail_light = %b, Time %d" , brake, turn_right, turn_left, right_tail_light_controll, left_tail_light_controll, $time);
    end

    initial begin
        #10
        rst_n = 1;

        #100 
        brake = 1;
        turn_left = 0;
        turn_right = 0;
        
        #100 
        brake = 0;
        turn_left = 1;
        turn_right = 0;

        #100 
        brake = 0;
        turn_left = 0;
        turn_right = 1;

        #100 
        brake = 1;
        turn_left = 1;
        turn_right = 0;

        #100 
        brake = 1;
        turn_left = 0;
        turn_right = 1;

        #100 
        brake = 0;
        turn_left = 1;
        turn_right = 0;

        #3 
        brake = 1;
        turn_left = 1;
        turn_right = 0;

        #100 
        brake = 0;
        turn_left = 0;
        turn_right = 1;

        #3 
        brake = 1;
        turn_left = 0;
        turn_right = 1;

        #100
        $finish;
    
    end

    endmodule

project2/simulation/work/tail_light_sequencer_tb.vcd
$date
    Sep 28, 2023  14:25:55
$end
$version
    TOOL:	xmsim(64)	17.10-s001
$end
$timescale
    1 ps
$end

$scope module tail_light_sequencer_tb $end
$var reg       1 !    clk $end
$var reg       1 "    rst_n $end
$var reg       1 #    brake $end
$var reg       1 $    turn_left $end
$var reg       1 %    turn_right $end
$var wire      3 &    right_tail_light_controll [2:0] $end
$var wire      3 '    left_tail_light_controll [2:0] $end

$scope module sequencer $end
$var wire      1 (    clk  $end
$var wire      1 )    rst_n  $end
$var wire      1 *    brake  $end
$var wire      1 +    turn_right  $end
$var wire      1 ,    turn_left  $end
$var reg       3 -    right_tail_light_controll [2:0] $end
$var reg       3 .    left_tail_light_controll [2:0] $end
$var parameter  5 /    idle $end
$var parameter  5 0    brake_only $end
$var parameter  5 1    right_only $end
$var parameter  5 2    left_only $end
$var parameter  5 3    brake_right $end
$var parameter  5 4    brake_left $end
$var reg       5 5    state [4:0] $end
$var reg       5 6    next [4:0] $end
$var wire      1 7    next_stage  $end
$var reg       5 8    counter [4:0] $end
$var reg       3 9    right_tail_light_controll_next [2:0] $end
$var reg       3 :    left_tail_light_controll_next [2:0] $end
$upscope $end

$upscope $end

$enddefinitions $end
$dumpvars
b10000 4
b1000 3
b100 2
b10 1
b1 0
b0 /
0!
0"
0#
0$
0%
b0 &
b0 '
0(
0)
0*
0+
0,
b0 -
b0 .
b0 5
b0 6
07
b1 8
b0 9
b0 :
$end
#1000
1!
1(
#2000
0!
0(
#3000
1!
1(
#4000
0!
0(
#5000
1!
1(
#6000
0!
0(
#7000
1!
1(
#8000
0!
0(
#9000
1!
1(
#10000
1"
0!
0(
1)
#11000
1!
1(
b10 8
#12000
0!
0(
#13000
1!
1(
b100 8
#14000
0!
0(
#15000
1!
1(
b1000 8
#16000
0!
0(
#17000
1!
1(
b10000 8
17
#18000
0!
0(
#19000
1!
1(
b1 8
07
#20000
0!
0(
#21000
1!
1(
b10 8
#22000
0!
0(
#23000
1!
1(
b100 8
#24000
0!
0(
#25000
1!
1(
b1000 8
#26000
0!
0(
#27000
1!
1(
b10000 8
17
#28000
0!
0(
#29000
1!
1(
b1 8
07
#30000
0!
0(
#31000
1!
1(
b10 8
#32000
0!
0(
#33000
1!
1(
b100 8
#34000
0!
0(
#35000
1!
1(
b1000 8
#36000
0!
0(
#37000
1!
1(
b10000 8
17
#38000
0!
0(
#39000
1!
1(
b1 8
07
#40000
0!
0(
#41000
1!
1(
b10 8
#42000
0!
0(
#43000
1!
1(
b100 8
#44000
0!
0(
#45000
1!
1(
b1000 8
#46000
0!
0(
#47000
1!
1(
b10000 8
17
#48000
0!
0(
#49000
1!
1(
b1 8
07
#50000
0!
0(
#51000
1!
1(
b10 8
#52000
0!
0(
#53000
1!
1(
b100 8
#54000
0!
0(
#55000
1!
1(
b1000 8
#56000
0!
0(
#57000
1!
1(
b10000 8
17
#58000
0!
0(
#59000
1!
1(
b1 8
07
#60000
0!
0(
#61000
1!
1(
b10 8
#62000
0!
0(
#63000
1!
1(
b100 8
#64000
0!
0(
#65000
1!
1(
b1000 8
#66000
0!
0(
#67000
1!
1(
b10000 8
17
#68000
0!
0(
#69000
1!
1(
b1 8
07
#70000
0!
0(
#71000
1!
1(
b10 8
#72000
0!
0(
#73000
1!
1(
b100 8
#74000
0!
0(
#75000
1!
1(
b1000 8
#76000
0!
0(
#77000
1!
1(
b10000 8
17
#78000
0!
0(
#79000
1!
1(
b1 8
07
#80000
0!
0(
#81000
1!
1(
b10 8
#82000
0!
0(
#83000
1!
1(
b100 8
#84000
0!
0(
#85000
1!
1(
b1000 8
#86000
0!
0(
#87000
1!
1(
b10000 8
17
#88000
0!
0(
#89000
1!
1(
b1 8
07
#90000
0!
0(
#91000
1!
1(
b10 8
#92000
0!
0(
#93000
1!
1(
b100 8
#94000
0!
0(
#95000
1!
1(
b1000 8
#96000
0!
0(
#97000
1!
1(
b10000 8
17
#98000
0!
0(
#99000
1!
1(
b1 8
07
#100000
0!
0(
#101000
1!
1(
b10 8
#102000
0!
0(
#103000
1!
1(
b100 8
#104000
0!
0(
#105000
1!
1(
b1000 8
#106000
0!
0(
#107000
1!
1(
b10000 8
17
#108000
0!
0(
#109000
1!
1(
b1 8
07
#110000
1#
0!
1*
0(
b1 6
b111 9
b111 :
#111000
1!
1(
b111 -
b111 .
b1 5
b111 '
b111 &
#112000
0!
0(
#113000
1!
1(
b10 8
#114000
0!
0(
#115000
1!
1(
b100 8
#116000
0!
0(
#117000
1!
1(
b1000 8
#118000
0!
0(
#119000
1!
1(
b10000 8
17
#120000
0!
0(
#121000
1!
1(
b1 8
07
#122000
0!
0(
#123000
1!
1(
b10 8
#124000
0!
0(
#125000
1!
1(
b100 8
#126000
0!
0(
#127000
1!
1(
b1000 8
#128000
0!
0(
#129000
1!
1(
b10000 8
17
#130000
0!
0(
#131000
1!
1(
b1 8
07
#132000
0!
0(
#133000
1!
1(
b10 8
#134000
0!
0(
#135000
1!
1(
b100 8
#136000
0!
0(
#137000
1!
1(
b1000 8
#138000
0!
0(
#139000
1!
1(
b10000 8
17
#140000
0!
0(
#141000
1!
1(
b1 8
07
#142000
0!
0(
#143000
1!
1(
b10 8
#144000
0!
0(
#145000
1!
1(
b100 8
#146000
0!
0(
#147000
1!
1(
b1000 8
#148000
0!
0(
#149000
1!
1(
b10000 8
17
#150000
0!
0(
#151000
1!
1(
b1 8
07
#152000
0!
0(
#153000
1!
1(
b10 8
#154000
0!
0(
#155000
1!
1(
b100 8
#156000
0!
0(
#157000
1!
1(
b1000 8
#158000
0!
0(
#159000
1!
1(
b10000 8
17
#160000
0!
0(
#161000
1!
1(
b1 8
07
#162000
0!
0(
#163000
1!
1(
b10 8
#164000
0!
0(
#165000
1!
1(
b100 8
#166000
0!
0(
#167000
1!
1(
b1000 8
#168000
0!
0(
#169000
1!
1(
b10000 8
17
#170000
0!
0(
#171000
1!
1(
b1 8
07
#172000
0!
0(
#173000
1!
1(
b10 8
#174000
0!
0(
#175000
1!
1(
b100 8
#176000
0!
0(
#177000
1!
1(
b1000 8
#178000
0!
0(
#179000
1!
1(
b10000 8
17
#180000
0!
0(
#181000
1!
1(
b1 8
07
#182000
0!
0(
#183000
1!
1(
b10 8
#184000
0!
0(
#185000
1!
1(
b100 8
#186000
0!
0(
#187000
1!
1(
b1000 8
#188000
0!
0(
#189000
1!
1(
b10000 8
17
#190000
0!
0(
#191000
1!
1(
b1 8
07
#192000
0!
0(
#193000
1!
1(
b10 8
#194000
0!
0(
#195000
1!
1(
b100 8
#196000
0!
0(
#197000
1!
1(
b1000 8
#198000
0!
0(
#199000
1!
1(
b10000 8
17
#200000
0!
0(
#201000
1!
1(
b1 8
07
#202000
0!
0(
#203000
1!
1(
b10 8
#204000
0!
0(
#205000
1!
1(
b100 8
#206000
0!
0(
#207000
1!
1(
b1000 8
#208000
0!
0(
#209000
1!
1(
b10000 8
17
#210000
0#
1$
0!
1,
0*
0(
b100 6
b1 :
b0 9
#211000
1!
1(
b0 -
b1 .
b100 5
b1 8
07
b1 '
b0 &
#212000
0!
0(
#213000
1!
1(
b10 8
#214000
0!
0(
#215000
1!
1(
b100 8
#216000
0!
0(
#217000
1!
1(
b1000 8
#218000
0!
0(
#219000
1!
1(
b10000 8
17
b11 :
#220000
0!
0(
#221000
1!
1(
b11 .
b1 8
07
b11 '
#222000
0!
0(
#223000
1!
1(
b10 8
#224000
0!
0(
#225000
1!
1(
b100 8
#226000
0!
0(
#227000
1!
1(
b1000 8
#228000
0!
0(
#229000
1!
1(
b10000 8
17
b111 :
#230000
0!
0(
#231000
1!
1(
b111 .
b1 8
07
b111 '
#232000
0!
0(
#233000
1!
1(
b10 8
#234000
0!
0(
#235000
1!
1(
b100 8
#236000
0!
0(
#237000
1!
1(
b1000 8
#238000
0!
0(
#239000
1!
1(
b10000 8
17
b0 :
#240000
0!
0(
#241000
1!
1(
b0 .
b1 8
07
b0 '
#242000
0!
0(
#243000
1!
1(
b10 8
#244000
0!
0(
#245000
1!
1(
b100 8
#246000
0!
0(
#247000
1!
1(
b1000 8
#248000
0!
0(
#249000
1!
1(
b10000 8
17
b1 :
#250000
0!
0(
#251000
1!
1(
b1 .
b1 8
07
b1 '
#252000
0!
0(
#253000
1!
1(
b10 8
#254000
0!
0(
#255000
1!
1(
b100 8
#256000
0!
0(
#257000
1!
1(
b1000 8
#258000
0!
0(
#259000
1!
1(
b10000 8
17
b11 :
#260000
0!
0(
#261000
1!
1(
b11 .
b1 8
07
b11 '
#262000
0!
0(
#263000
1!
1(
b10 8
#264000
0!
0(
#265000
1!
1(
b100 8
#266000
0!
0(
#267000
1!
1(
b1000 8
#268000
0!
0(
#269000
1!
1(
b10000 8
17
b111 :
#270000
0!
0(
#271000
1!
1(
b111 .
b1 8
07
b111 '
#272000
0!
0(
#273000
1!
1(
b10 8
#274000
0!
0(
#275000
1!
1(
b100 8
#276000
0!
0(
#277000
1!
1(
b1000 8
#278000
0!
0(
#279000
1!
1(
b10000 8
17
b0 :
#280000
0!
0(
#281000
1!
1(
b0 .
b1 8
07
b0 '
#282000
0!
0(
#283000
1!
1(
b10 8
#284000
0!
0(
#285000
1!
1(
b100 8
#286000
0!
0(
#287000
1!
1(
b1000 8
#288000
0!
0(
#289000
1!
1(
b10000 8
17
b1 :
#290000
0!
0(
#291000
1!
1(
b1 .
b1 8
07
b1 '
#292000
0!
0(
#293000
1!
1(
b10 8
#294000
0!
0(
#295000
1!
1(
b100 8
#296000
0!
0(
#297000
1!
1(
b1000 8
#298000
0!
0(
#299000
1!
1(
b10000 8
17
b11 :
#300000
0!
0(
#301000
1!
1(
b11 .
b1 8
07
b11 '
#302000
0!
0(
#303000
1!
1(
b10 8
#304000
0!
0(
#305000
1!
1(
b100 8
#306000
0!
0(
#307000
1!
1(
b1000 8
#308000
0!
0(
#309000
1!
1(
b10000 8
17
b111 :
#310000
0$
1%
0!
1+
0,
0(
b10 6
b1 9
b0 :
#311000
1!
1(
b1 -
b0 .
b10 5
b1 8
07
b0 '
b1 &
#312000
0!
0(
#313000
1!
1(
b10 8
#314000
0!
0(
#315000
1!
1(
b100 8
#316000
0!
0(
#317000
1!
1(
b1000 8
#318000
0!
0(
#319000
1!
1(
b10000 8
17
b11 9
#320000
0!
0(
#321000
1!
1(
b11 -
b1 8
07
b11 &
#322000
0!
0(
#323000
1!
1(
b10 8
#324000
0!
0(
#325000
1!
1(
b100 8
#326000
0!
0(
#327000
1!
1(
b1000 8
#328000
0!
0(
#329000
1!
1(
b10000 8
17
b111 9
#330000
0!
0(
#331000
1!
1(
b111 -
b1 8
07
b111 &
#332000
0!
0(
#333000
1!
1(
b10 8
#334000
0!
0(
#335000
1!
1(
b100 8
#336000
0!
0(
#337000
1!
1(
b1000 8
#338000
0!
0(
#339000
1!
1(
b10000 8
17
b0 9
#340000
0!
0(
#341000
1!
1(
b0 -
b1 8
07
b0 &
#342000
0!
0(
#343000
1!
1(
b10 8
#344000
0!
0(
#345000
1!
1(
b100 8
#346000
0!
0(
#347000
1!
1(
b1000 8
#348000
0!
0(
#349000
1!
1(
b10000 8
17
b1 9
#350000
0!
0(
#351000
1!
1(
b1 -
b1 8
07
b1 &
#352000
0!
0(
#353000
1!
1(
b10 8
#354000
0!
0(
#355000
1!
1(
b100 8
#356000
0!
0(
#357000
1!
1(
b1000 8
#358000
0!
0(
#359000
1!
1(
b10000 8
17
b11 9
#360000
0!
0(
#361000
1!
1(
b11 -
b1 8
07
b11 &
#362000
0!
0(
#363000
1!
1(
b10 8
#364000
0!
0(
#365000
1!
1(
b100 8
#366000
0!
0(
#367000
1!
1(
b1000 8
#368000
0!
0(
#369000
1!
1(
b10000 8
17
b111 9
#370000
0!
0(
#371000
1!
1(
b111 -
b1 8
07
b111 &
#372000
0!
0(
#373000
1!
1(
b10 8
#374000
0!
0(
#375000
1!
1(
b100 8
#376000
0!
0(
#377000
1!
1(
b1000 8
#378000
0!
0(
#379000
1!
1(
b10000 8
17
b0 9
#380000
0!
0(
#381000
1!
1(
b0 -
b1 8
07
b0 &
#382000
0!
0(
#383000
1!
1(
b10 8
#384000
0!
0(
#385000
1!
1(
b100 8
#386000
0!
0(
#387000
1!
1(
b1000 8
#388000
0!
0(
#389000
1!
1(
b10000 8
17
b1 9
#390000
0!
0(
#391000
1!
1(
b1 -
b1 8
07
b1 &
#392000
0!
0(
#393000
1!
1(
b10 8
#394000
0!
0(
#395000
1!
1(
b100 8
#396000
0!
0(
#397000
1!
1(
b1000 8
#398000
0!
0(
#399000
1!
1(
b10000 8
17
b11 9
#400000
0!
0(
#401000
1!
1(
b11 -
b1 8
07
b11 &
#402000
0!
0(
#403000
1!
1(
b10 8
#404000
0!
0(
#405000
1!
1(
b100 8
#406000
0!
0(
#407000
1!
1(
b1000 8
#408000
0!
0(
#409000
1!
1(
b10000 8
17
b111 9
#410000
1#
1$
0%
0!
0+
1,
1*
0(
b10000 6
b111 :
#411000
1!
1(
b111 -
b111 .
b10000 5
b1 8
07
b111 '
b111 &
#412000
0!
0(
#413000
1!
1(
b10 8
#414000
0!
0(
#415000
1!
1(
b100 8
#416000
0!
0(
#417000
1!
1(
b1000 8
#418000
0!
0(
#419000
1!
1(
b10000 8
17
b110 :
#420000
0!
0(
#421000
1!
1(
b110 .
b1 8
07
b110 '
#422000
0!
0(
#423000
1!
1(
b10 8
#424000
0!
0(
#425000
1!
1(
b100 8
#426000
0!
0(
#427000
1!
1(
b1000 8
#428000
0!
0(
#429000
1!
1(
b10000 8
17
b100 :
#430000
0!
0(
#431000
1!
1(
b100 .
b1 8
07
b100 '
#432000
0!
0(
#433000
1!
1(
b10 8
#434000
0!
0(
#435000
1!
1(
b100 8
#436000
0!
0(
#437000
1!
1(
b1000 8
#438000
0!
0(
#439000
1!
1(
b10000 8
17
b0 :
#440000
0!
0(
#441000
1!
1(
b0 .
b1 8
07
b0 '
#442000
0!
0(
#443000
1!
1(
b10 8
#444000
0!
0(
#445000
1!
1(
b100 8
#446000
0!
0(
#447000
1!
1(
b1000 8
#448000
0!
0(
#449000
1!
1(
b10000 8
17
b111 :
#450000
0!
0(
#451000
1!
1(
b111 .
b1 8
07
b111 '
#452000
0!
0(
#453000
1!
1(
b10 8
#454000
0!
0(
#455000
1!
1(
b100 8
#456000
0!
0(
#457000
1!
1(
b1000 8
#458000
0!
0(
#459000
1!
1(
b10000 8
17
b110 :
#460000
0!
0(
#461000
1!
1(
b110 .
b1 8
07
b110 '
#462000
0!
0(
#463000
1!
1(
b10 8
#464000
0!
0(
#465000
1!
1(
b100 8
#466000
0!
0(
#467000
1!
1(
b1000 8
#468000
0!
0(
#469000
1!
1(
b10000 8
17
b100 :
#470000
0!
0(
#471000
1!
1(
b100 .
b1 8
07
b100 '
#472000
0!
0(
#473000
1!
1(
b10 8
#474000
0!
0(
#475000
1!
1(
b100 8
#476000
0!
0(
#477000
1!
1(
b1000 8
#478000
0!
0(
#479000
1!
1(
b10000 8
17
b0 :
#480000
0!
0(
#481000
1!
1(
b0 .
b1 8
07
b0 '
#482000
0!
0(
#483000
1!
1(
b10 8
#484000
0!
0(
#485000
1!
1(
b100 8
#486000
0!
0(
#487000
1!
1(
b1000 8
#488000
0!
0(
#489000
1!
1(
b10000 8
17
b111 :
#490000
0!
0(
#491000
1!
1(
b111 .
b1 8
07
b111 '
#492000
0!
0(
#493000
1!
1(
b10 8
#494000
0!
0(
#495000
1!
1(
b100 8
#496000
0!
0(
#497000
1!
1(
b1000 8
#498000
0!
0(
#499000
1!
1(
b10000 8
17
b110 :
#500000
0!
0(
#501000
1!
1(
b110 .
b1 8
07
b110 '
#502000
0!
0(
#503000
1!
1(
b10 8
#504000
0!
0(
#505000
1!
1(
b100 8
#506000
0!
0(
#507000
1!
1(
b1000 8
#508000
0!
0(
#509000
1!
1(
b10000 8
17
b100 :
#510000
0$
1%
0!
1+
0,
0(
b1000 6
b111 :
#511000
1!
1(
b111 .
b1000 5
b1 8
07
b111 '
#512000
0!
0(
#513000
1!
1(
b10 8
#514000
0!
0(
#515000
1!
1(
b100 8
#516000
0!
0(
#517000
1!
1(
b1000 8
#518000
0!
0(
#519000
1!
1(
b10000 8
17
b110 9
#520000
0!
0(
#521000
1!
1(
b110 -
b1 8
07
b110 &
#522000
0!
0(
#523000
1!
1(
b10 8
#524000
0!
0(
#525000
1!
1(
b100 8
#526000
0!
0(
#527000
1!
1(
b1000 8
#528000
0!
0(
#529000
1!
1(
b10000 8
17
b100 9
#530000
0!
0(
#531000
1!
1(
b100 -
b1 8
07
b100 &
#532000
0!
0(
#533000
1!
1(
b10 8
#534000
0!
0(
#535000
1!
1(
b100 8
#536000
0!
0(
#537000
1!
1(
b1000 8
#538000
0!
0(
#539000
1!
1(
b10000 8
17
b0 9
#540000
0!
0(
#541000
1!
1(
b0 -
b1 8
07
b0 &
#542000
0!
0(
#543000
1!
1(
b10 8
#544000
0!
0(
#545000
1!
1(
b100 8
#546000
0!
0(
#547000
1!
1(
b1000 8
#548000
0!
0(
#549000
1!
1(
b10000 8
17
b111 9
#550000
0!
0(
#551000
1!
1(
b111 -
b1 8
07
b111 &
#552000
0!
0(
#553000
1!
1(
b10 8
#554000
0!
0(
#555000
1!
1(
b100 8
#556000
0!
0(
#557000
1!
1(
b1000 8
#558000
0!
0(
#559000
1!
1(
b10000 8
17
b110 9
#560000
0!
0(
#561000
1!
1(
b110 -
b1 8
07
b110 &
#562000
0!
0(
#563000
1!
1(
b10 8
#564000
0!
0(
#565000
1!
1(
b100 8
#566000
0!
0(
#567000
1!
1(
b1000 8
#568000
0!
0(
#569000
1!
1(
b10000 8
17
b100 9
#570000
0!
0(
#571000
1!
1(
b100 -
b1 8
07
b100 &
#572000
0!
0(
#573000
1!
1(
b10 8
#574000
0!
0(
#575000
1!
1(
b100 8
#576000
0!
0(
#577000
1!
1(
b1000 8
#578000
0!
0(
#579000
1!
1(
b10000 8
17
b0 9
#580000
0!
0(
#581000
1!
1(
b0 -
b1 8
07
b0 &
#582000
0!
0(
#583000
1!
1(
b10 8
#584000
0!
0(
#585000
1!
1(
b100 8
#586000
0!
0(
#587000
1!
1(
b1000 8
#588000
0!
0(
#589000
1!
1(
b10000 8
17
b111 9
#590000
0!
0(
#591000
1!
1(
b111 -
b1 8
07
b111 &
#592000
0!
0(
#593000
1!
1(
b10 8
#594000
0!
0(
#595000
1!
1(
b100 8
#596000
0!
0(
#597000
1!
1(
b1000 8
#598000
0!
0(
#599000
1!
1(
b10000 8
17
b110 9
#600000
0!
0(
#601000
1!
1(
b110 -
b1 8
07
b110 &
#602000
0!
0(
#603000
1!
1(
b10 8
#604000
0!
0(
#605000
1!
1(
b100 8
#606000
0!
0(
#607000
1!
1(
b1000 8
#608000
0!
0(
#609000
1!
1(
b10000 8
17
b100 9
#610000
0#
1$
0%
0!
0+
1,
0*
0(
b100 6
b1 :
b0 9
#611000
1!
1(
b0 -
b1 .
b100 5
b1 8
07
b1 '
b0 &
#612000
0!
0(
#613000
1#
1!
1*
1(
b10000 6
b10000 5
b111 :
b111 9
b1 :
#614000
0!
0(
#615000
1!
1(
b111 -
b10 8
b111 &
#616000
0!
0(
#617000
1!
1(
b100 8
#618000
0!
0(
#619000
1!
1(
b1000 8
#620000
0!
0(
#621000
1!
1(
b10000 8
17
#622000
0!
0(
#623000
1!
1(
b1 8
07
#624000
0!
0(
#625000
1!
1(
b10 8
#626000
0!
0(
#627000
1!
1(
b100 8
#628000
0!
0(
#629000
1!
1(
b1000 8
#630000
0!
0(
#631000
1!
1(
b10000 8
17
#632000
0!
0(
#633000
1!
1(
b1 8
07
#634000
0!
0(
#635000
1!
1(
b10 8
#636000
0!
0(
#637000
1!
1(
b100 8
#638000
0!
0(
#639000
1!
1(
b1000 8
#640000
0!
0(
#641000
1!
1(
b10000 8
17
#642000
0!
0(
#643000
1!
1(
b1 8
07
#644000
0!
0(
#645000
1!
1(
b10 8
#646000
0!
0(
#647000
1!
1(
b100 8
#648000
0!
0(
#649000
1!
1(
b1000 8
#650000
0!
0(
#651000
1!
1(
b10000 8
17
#652000
0!
0(
#653000
1!
1(
b1 8
07
#654000
0!
0(
#655000
1!
1(
b10 8
#656000
0!
0(
#657000
1!
1(
b100 8
#658000
0!
0(
#659000
1!
1(
b1000 8
#660000
0!
0(
#661000
1!
1(
b10000 8
17
#662000
0!
0(
#663000
1!
1(
b1 8
07
#664000
0!
0(
#665000
1!
1(
b10 8
#666000
0!
0(
#667000
1!
1(
b100 8
#668000
0!
0(
#669000
1!
1(
b1000 8
#670000
0!
0(
#671000
1!
1(
b10000 8
17
#672000
0!
0(
#673000
1!
1(
b1 8
07
#674000
0!
0(
#675000
1!
1(
b10 8
#676000
0!
0(
#677000
1!
1(
b100 8
#678000
0!
0(
#679000
1!
1(
b1000 8
#680000
0!
0(
#681000
1!
1(
b10000 8
17
#682000
0!
0(
#683000
1!
1(
b1 8
07
#684000
0!
0(
#685000
1!
1(
b10 8
#686000
0!
0(
#687000
1!
1(
b100 8
#688000
0!
0(
#689000
1!
1(
b1000 8
#690000
0!
0(
#691000
1!
1(
b10000 8
17
#692000
0!
0(
#693000
1!
1(
b1 8
07
#694000
0!
0(
#695000
1!
1(
b10 8
#696000
0!
0(
#697000
1!
1(
b100 8
#698000
0!
0(
#699000
1!
1(
b1000 8
#700000
0!
0(
#701000
1!
1(
b10000 8
17
#702000
0!
0(
#703000
1!
1(
b1 8
07
#704000
0!
0(
#705000
1!
1(
b10 8
#706000
0!
0(
#707000
1!
1(
b100 8
#708000
0!
0(
#709000
1!
1(
b1000 8
#710000
0!
0(
#711000
1!
1(
b10000 8
17
#712000
0!
0(
#713000
0#
0$
1%
1!
1+
0,
0*
1(
b10 6
b10 5
b1 8
b1 9
b0 :
07
b111 9
#714000
0!
0(
#715000
1!
1(
b0 .
b10 8
b0 '
#716000
1#
0!
1*
0(
b1000 6
b111 :
#717000
1!
1(
b111 .
b1000 5
b1 8
b111 '
#718000
0!
0(
#719000
1!
1(
b10 8
#720000
0!
0(
#721000
1!
1(
b100 8
#722000
0!
0(
#723000
1!
1(
b1000 8
#724000
0!
0(
#725000
1!
1(
b10000 8
17
b110 9
#726000
0!
0(
#727000
1!
1(
b110 -
b1 8
07
b110 &
#728000
0!
0(
#729000
1!
1(
b10 8
#730000
0!
0(
#731000
1!
1(
b100 8
#732000
0!
0(
#733000
1!
1(
b1000 8
#734000
0!
0(
#735000
1!
1(
b10000 8
17
b100 9
#736000
0!
0(
#737000
1!
1(
b100 -
b1 8
07
b100 &
#738000
0!
0(
#739000
1!
1(
b10 8
#740000
0!
0(
#741000
1!
1(
b100 8
#742000
0!
0(
#743000
1!
1(
b1000 8
#744000
0!
0(
#745000
1!
1(
b10000 8
17
b0 9
#746000
0!
0(
#747000
1!
1(
b0 -
b1 8
07
b0 &
#748000
0!
0(
#749000
1!
1(
b10 8
#750000
0!
0(
#751000
1!
1(
b100 8
#752000
0!
0(
#753000
1!
1(
b1000 8
#754000
0!
0(
#755000
1!
1(
b10000 8
17
b111 9
#756000
0!
0(
#757000
1!
1(
b111 -
b1 8
07
b111 &
#758000
0!
0(
#759000
1!
1(
b10 8
#760000
0!
0(
#761000
1!
1(
b100 8
#762000
0!
0(
#763000
1!
1(
b1000 8
#764000
0!
0(
#765000
1!
1(
b10000 8
17
b110 9
#766000
0!
0(
#767000
1!
1(
b110 -
b1 8
07
b110 &
#768000
0!
0(
#769000
1!
1(
b10 8
#770000
0!
0(
#771000
1!
1(
b100 8
#772000
0!
0(
#773000
1!
1(
b1000 8
#774000
0!
0(
#775000
1!
1(
b10000 8
17
b100 9
#776000
0!
0(
#777000
1!
1(
b100 -
b1 8
07
b100 &
#778000
0!
0(
#779000
1!
1(
b10 8
#780000
0!
0(
#781000
1!
1(
b100 8
#782000
0!
0(
#783000
1!
1(
b1000 8
#784000
0!
0(
#785000
1!
1(
b10000 8
17
b0 9
#786000
0!
0(
#787000
1!
1(
b0 -
b1 8
07
b0 &
#788000
0!
0(
#789000
1!
1(
b10 8
#790000
0!
0(
#791000
1!
1(
b100 8
#792000
0!
0(
#793000
1!
1(
b1000 8
#794000
0!
0(
#795000
1!
1(
b10000 8
17
b111 9
#796000
0!
0(
#797000
1!
1(
b111 -
b1 8
07
b111 &
#798000
0!
0(
#799000
1!
1(
b10 8
#800000
0!
0(
#801000
1!
1(
b100 8
#802000
0!
0(
